shellrunner/__init__.py
shellrunner/config.py
shellrunner/db.py
shellrunner/menu.py
shellrunner/runner.py
shellrunner/shellrunner.py
shellrunner/util/__init__.py
shellrunner/util/dict.py
shellrunner-0.6.0.dist-info/LICENSE.txt
shellrunner-0.6.0.dist-info/METADATA
shellrunner-0.6.0.dist-info/WHEEL
shellrunner-0.6.0.dist-info/entry_points.txt
shellrunner-0.6.0.dist-info/top_level.txt
shellrunner-0.6.0.dist-info/RECORD
