Metadata-Version: 2.1
Name: shellrunner
Version: 0.6.0
Summary: Speed up your shell activity
Home-page: https://github.com/dtrugman/shellrunner
Author: Daniel Trugman
Author-email: dtrugman@gmail.com
License: UNKNOWN
Keywords: shell,runner
Platform: UNKNOWN
Classifier: Development Status :: 3 - Alpha
Classifier: Programming Language :: Python :: 3
Classifier: License :: OSI Approved :: MIT License
Classifier: Operating System :: OS Independent
